captcha/__init__.py
captcha/_compat.py
captcha/apps.py
captcha/checks.py
captcha/client.py
captcha/constants.py
captcha/decorators.py
captcha/fields.py
captcha/models.py
captcha/widgets.py
captcha/locale/el/LC_MESSAGES/django.po
captcha/locale/en/LC_MESSAGES/django.po
captcha/locale/es/LC_MESSAGES/django.po
captcha/locale/fr/LC_MESSAGES/django.po
captcha/locale/nl/LC_MESSAGES/django.po
captcha/locale/pl/LC_MESSAGES/django.po
captcha/locale/pt_BR/LC_MESSAGES/django.po
captcha/locale/ru/LC_MESSAGES/django.po
captcha/locale/zh_CN/LC_MESSAGES/django.po
captcha/locale/zh_TW/LC_MESSAGES/django.po
captcha/templates/captcha/widget_v2_checkbox.html
captcha/templates/captcha/widget_v2_invisible.html
captcha/templates/captcha/widget_v3.html
captcha/templates/captcha/includes/js_v2_checkbox.html
captcha/templates/captcha/includes/js_v2_invisible.html
captcha/templates/captcha/includes/js_v3.html
captcha/tests/__init__.py
captcha/tests/test_client.py
captcha/tests/test_fields.py
captcha/tests/tests.py
captcha/tests/requirements/py27.txt
captcha/tests/settings/__init__.py
captcha/tests/settings/coveralls_settings.py
django_recaptcha_enterprise-0.0.14.dist-info/METADATA
django_recaptcha_enterprise-0.0.14.dist-info/WHEEL
django_recaptcha_enterprise-0.0.14.dist-info/top_level.txt
django_recaptcha_enterprise-0.0.14.dist-info/RECORD
